Workbook
Name aporte: 'Controle de investimentos'!$D$12
Name patrimonio: 'Controle de investimentos'!$D$15
Name qnt_anos: 'Controle de investimentos'!$D$13
Name rendimento_carteira: 'Controle de investimentos'!$D$8
Name salario: 'Controle de investimentos'!$D$7
Name sugestao_investimento: 'Controle de investimentos'!$D$9
Name taxa_mensal: 'Controle de investimentos'!$D$14

Sheet Controle de investimentos
B6: CONFIGURAÇÕES
B7: Salário | D7: 5000
B8: Rendimento carteira | D8: 0.006
B9: Sugestão investimento (30%) | D9: =D7*30% -> 1500
B11: INVESTIMENTO MENSAL
B12: Quanto devo investir por mês? | D12: 500
B13: Por quantos anos? | D13: 5
B14: Taxa de rendimento mensal? | D14: 0.01079
B15: Patrimônio acumulado | D15: =FV(taxa_mensal,qnt_anos*12,aporte*-1) -> 41888.457
B16: Dividendos mensais | D16: =patrimonio*rendimento_carteira -> 251.33074
B18: CENÁRIOS | D18: Dividendo
A19: 2 | B19: Quanto em 2 anos | C19: =FV($D$14,$A19*12,$D$12*-1) -> 13613.814 | D19: =C19*rendimento_carteira -> 81.682882
A20: 5 | B20: Quanto em 5 anos | C20: =FV($D$14,$A20*12,$D$12*-1) -> 41888.457 | D20: =C20*rendimento_carteira -> 251.33074
A21: 10 | B21: Quanto em 10 anos | C21: =FV($D$14,$A21*12,$D$12*-1) -> 121642.11 | D21: =C21*rendimento_carteira -> 729.85264
A22: 20 | B22: Quanto em 20 anos | C22: =FV($D$14,$A22*12,$D$12*-1) -> 562599.2 | D22: =C22*rendimento_carteira -> 3375.5952
A23: 30 | B23: Quanto em 30 anos | C23: =FV($D$14,$A23*12,$D$12*-1) -> 2161084.8 | D23: =C23*rendimento_carteira -> 12966.509
B25: PERFIL | D25: Conservador
B26: Valor a ser investido por mês | D26: =aporte -> 500
B28: TIPO DE FII | C28: Percentual Sugerido | D28: Valores
B29: PAPEL | C29: =VLOOKUP($D$25&"-"&B29,Apoio!A2:D20,4,FALSE) -> 0.3 | D29: =C29*$D$26 -> 150
B30: TIJOLO | C30: =VLOOKUP($D$25&"-"&B30,Apoio!A3:D21,4,FALSE) -> 0.5 | D30: =C30*$D$26 -> 250
B31: HIBRIDOS | C31: =VLOOKUP($D$25&"-"&B31,Apoio!A4:D22,4,FALSE) -> 0.1 | D31: =C31*$D$26 -> 50
B32: FOFs | C32: =VLOOKUP($D$25&"-"&B32,Apoio!A5:D23,4,FALSE) -> 0.1 | D32: =C32*$D$26 -> 50
B33: DESENVOLVIMENTO | C33: =VLOOKUP($D$25&"-"&B33,Apoio!A6:D24,4,FALSE) -> 0 | D33: =C33*$D$26 -> 0
B34: HOTELARIAS | C34: =VLOOKUP($D$25&"-"&B34,Apoio!A7:D25,4,FALSE) -> 0 | D34: =C34*$D$26 -> 0
D35: =SUM(D29:D34) -> 500

Sheet Apoio
A2: CHAVE | B2: PERFIL | C2: TIPO DE FII | D2: %
A3: =B3&"-"&C3 -> Conservador-PAPEL | B3: Conservador | C3: PAPEL | D3: 0.3
A4: =B4&"-"&C4 -> Conservador-TIJOLO | B4: Conservador | C4: TIJOLO | D4: 0.5
A5: =B5&"-"&C5 -> Conservador-HIBRIDOS | B5: Conservador | C5: HIBRIDOS | D5: 0.1
A6: =B6&"-"&C6 -> Conservador-FOFs | B6: Conservador | C6: FOFs | D6: 0.1
A7: =B7&"-"&C7 -> Conservador-DESENVOLVIMENTO | B7: Conservador | C7: DESENVOLVIMENTO | D7: 0
A8: =B8&"-"&C8 -> Conservador-HOTELARIAS | B8: Conservador | C8: HOTELARIAS | D8: 0
A9: =B9&"-"&C9 -> Moderado-PAPEL | B9: Moderado | C9: PAPEL | D9: 0.32
A10: =B10&"-"&C10 -> Moderado-TIJOLO | B10: Moderado | C10: TIJOLO | D10: 0.35
A11: =B11&"-"&C11 -> Moderado-HIBRIDOS | B11: Moderado | C11: HIBRIDOS | D11: 0.08
A12: =B12&"-"&C12 -> Moderado-FOFs | B12: Moderado | C12: FOFs | D12: 0.05
A13: =B13&"-"&C13 -> Moderado-DESENVOLVIMENTO | B13: Moderado | C13: DESENVOLVIMENTO | D13: 0.1
A14: =B14&"-"&C14 -> Moderado-HOTELARIAS | B14: Moderado | C14: HOTELARIAS | D14: 0.1
... A20: =B20&"-"&C20 -> Agressivo-HOTELARIAS | B20: Agressivo | C20: HOTELARIAS | D20: 0.1
